jnorm/__init__.py
jnorm/main.py
jnorm-1.0.0.dist-info/LICENSE.txt
jnorm-1.0.0.dist-info/METADATA
jnorm-1.0.0.dist-info/WHEEL
jnorm-1.0.0.dist-info/entry_points.txt
jnorm-1.0.0.dist-info/top_level.txt
jnorm-1.0.0.dist-info/RECORD
