Metadata-Version: 2.1
Name: jnorm
Version: 1.0.0
Summary: Normalize deeply nested JSON files into flat JSONL files.
Author-email: Forrest Bajbek <forrestbajbek@gmail.com>
License: MIT
Classifier: Development Status :: 5 - Production/Stable
Classifier: License :: OSI Approved :: MIT License
Classifier: Programming Language :: Python
Classifier: Programming Language :: Python :: 3 :: Only
Classifier: Programming Language :: Python :: 3.9
Classifier: Programming Language :: Python :: 3.10
Classifier: Topic :: Database
Classifier: Topic :: Text Processing
Requires-Python: >=3.7
License-File: LICENSE.txt
Requires-Dist: ijson
Requires-Dist: rich
Provides-Extra: dev
Requires-Dist: black ; extra == 'dev'
Requires-Dist: ruff ; extra == 'dev'
